main.py
setup.py
dtb_bytehouse.egg-info/PKG-INFO
dtb_bytehouse.egg-info/SOURCES.txt
dtb_bytehouse.egg-info/dependency_links.txt
dtb_bytehouse.egg-info/requires.txt
dtb_bytehouse.egg-info/top_level.txt